perplexipy/__init__.py
perplexipy/coddex-WIP.py
perplexipy/codex.py
perplexipy/errors.py
perplexipy/responses.py
PerplexiPy-1.3.0.dist-info/LICENSE.txt
PerplexiPy-1.3.0.dist-info/METADATA
PerplexiPy-1.3.0.dist-info/WHEEL
PerplexiPy-1.3.0.dist-info/entry_points.txt
PerplexiPy-1.3.0.dist-info/top_level.txt
PerplexiPy-1.3.0.dist-info/RECORD
