Metadata-Version: 2.1
Name: PerplexiPy
Version: 1.3.0
Summary: PerplexiPy - A robust Perplexity AI API client
Author-email: CIME Software Ltd <perplexipy@cime.net>
License: BSD-3
Project-URL: homepage, https://cime-software.github.io/perplexipy/
Project-URL: Documentation, https://cime-software.github.io/perplexipy/
Project-URL: Bug Tracker, https://github.com/CIME-Software/perplexipy/issues
Project-URL: Source, https://github.com/CIME-Software/perplexipy
Classifier: Development Status :: 4 - Beta
Classifier: Intended Audience :: Developers
Classifier: License :: OSI Approved :: BSD License
Classifier: Operating System :: OS Independent
Classifier: Programming Language :: Python :: 3
Classifier: Programming Language :: Python :: 3.9
Classifier: Topic :: Scientific/Engineering :: Artificial Intelligence
Classifier: Topic :: Software Development :: Libraries :: Python Modules
Requires-Python: >=3.9
License-File: LICENSE.txt
Requires-Dist: appdirs
Requires-Dist: click
Requires-Dist: openai (>=1.12.0)
Requires-Dist: prompt-toolkit
Requires-Dist: python-dotenv
Requires-Dist: pyyaml
